preston/__init__.py
preston/cache.py
preston/preston.py
preston-4.12.1.dist-info/licenses/LICENSE
preston-4.12.1.dist-info/METADATA
preston-4.12.1.dist-info/WHEEL
preston-4.12.1.dist-info/top_level.txt
preston-4.12.1.dist-info/RECORD
