Metadata-Version: 2.4
Name: preston
Version: 4.12.1
Summary: EVE ESI API access tool
Author-email: Celeo <mattboulanger@fastmail.com>
License-Expression: MIT
Project-URL: homepage, https://github.com/Celeo/Preston
Project-URL: repository, https://github.com/Celeo/Preston
Keywords: eve online,eve,esi
Classifier: Environment :: Console
Classifier: Environment :: Web Environment
Classifier: Operating System :: OS Independent
Classifier: Programming Language :: Python :: 3
Classifier: Topic :: Software Development :: Libraries
Requires-Python: <4.0,>=3.11
License-File: LICENSE
Requires-Dist: cryptography>=44.0.3
Requires-Dist: pyjwt>=2.9.0
Requires-Dist: requests==2.32.3
Dynamic: license-file
